itk_isotropicwavelets-0.6.2.dist-info/RECORD
itk_isotropicwavelets-0.6.2.dist-info/LICENSE
itk_isotropicwavelets-0.6.2.dist-info/WHEEL
itk_isotropicwavelets-0.6.2.dist-info/top_level.txt
itk_isotropicwavelets-0.6.2.dist-info/METADATA
itk/itkFrequencyExpandImageFilterPython.py
itk/itkWaveletFrequencyInverseUndecimatedPython.py
itk/IsotropicWaveletsPython.py
itk/itkFrequencyFunctionPython.py
itk/itkFrequencyShrinkViaInverseFFTImageFilterPython.py
itk/itkHeldIsotropicWaveletPython.py
itk/itkSimoncelliIsotropicWaveletPython.py
itk/itkShannonIsotropicWaveletPython.py
itk/itkIsotropicFrequencyFunctionPython.py
itk/itkExpandWithZerosImageFilterPython.py
itk/itkShrinkDecimateImageFilterPython.py
itk/itkVariableSizeMatrixComplexPython.py
itk/itkFrequencyShrinkImageFilterPython.py
itk/itkStructureTensorImageFilterPython.py
itk/itkIsotropicWaveletFrequencyFunctionPython.py
itk/itkWaveletFrequencyInversePython.py
itk/itkPhaseAnalysisImageFilterPython.py
itk/itkPhaseAnalysisSoftThresholdImageFilterPython.py
itk/itkWaveletFrequencyForwardPython.py
itk/_IsotropicWaveletsPython.so
itk/itkWaveletFrequencyFilterBankGeneratorPython.py
itk/itkZeroDCImageFilterPython.py
itk/itkFrequencyExpandViaInverseFFTImageFilterPython.py
itk/itkRieszFrequencyFilterBankGeneratorPython.py
itk/itkVowIsotropicWaveletPython.py
itk/itkVectorInverseFFTImageFilterPython.py
itk/itkMatrixComplexPython.py
itk/itkWaveletFrequencyForwardUndecimatedPython.py
itk/itkMonogenicSignalFrequencyImageFilterPython.py
itk/itkIsotropicWaveletsUtilitiesPython.py
itk/itkRieszRotationMatrixPython.py
itk/Configuration/IsotropicWaveletsConfig.py
itk/Configuration/IsotropicWavelets_snake_case.py
itk/.dylibs/libtbb.12.3.dylib
