Metadata-Version: 2.1
Name: itk-isotropicwavelets
Version: 0.6.2
Summary: Steerable Wavelet Pyramid with Isotropic Wavelets and Riesz Functions
Home-page: https://github.com/InsightSoftwareConsortium/ITKIsotropicWavelets
Download-URL: https://github.com/InsightSoftwareConsortium/ITKIsotropicWavelets
Author: Pablo Hernandez-Cerdan
Author-email: pablo.hernandez.cerdan@outlook.com
License: Apache
Keywords: ITK InsightToolkit Wavelet Pyramid Steerable Riesz
Classifier: License :: OSI Approved :: Apache Software License
Classifier: Programming Language :: Python
Classifier: Programming Language :: C++
Classifier: Development Status :: 4 - Beta
Classifier: Intended Audience :: Developers
Classifier: Intended Audience :: Education
Classifier: Intended Audience :: Healthcare Industry
Classifier: Intended Audience :: Science/Research
Classifier: Topic :: Scientific/Engineering
Classifier: Topic :: Scientific/Engineering :: Medical Science Apps.
Classifier: Topic :: Scientific/Engineering :: Information Analysis
Classifier: Topic :: Software Development :: Libraries
Classifier: Operating System :: Android
Classifier: Operating System :: Microsoft :: Windows
Classifier: Operating System :: POSIX
Classifier: Operating System :: Unix
Classifier: Operating System :: MacOS
License-File: LICENSE
Requires-Dist: itk (>=5.3.0)
